live_coverage/__init__.py
live_coverage/__main__.py
live_coverage/live_coverage.py
live_coverage/live_coverage.cpython-310-x86_64-linux-gnu.so
live_coverage/live_coverage__mypyc.cpython-310-x86_64-linux-gnu.so
live_coverage-0.0.3.dist-info/entry_points.txt
live_coverage-0.0.3.dist-info/LICENSE
live_coverage-0.0.3.dist-info/WHEEL
live_coverage-0.0.3.dist-info/METADATA
live_coverage-0.0.3.dist-info/RECORD
